dpyConsole/__init__.py
dpyConsole/console.py
dpyConsole/converter.py
dpyConsole/errors.py
discord.py_Console-0.1.2.dist-info/METADATA
discord.py_Console-0.1.2.dist-info/WHEEL
discord.py_Console-0.1.2.dist-info/top_level.txt
discord.py_Console-0.1.2.dist-info/RECORD
