Metadata-Version: 2.1
Name: discord.py-Console
Version: 0.1.2
Summary: Executes commands from console while your bot is running.
Home-page: https://github.com/Mihitoko/discord.py-Console
Author: Mihito
License: MIT
Platform: UNKNOWN
Classifier: Programming Language :: Python :: 3.7
Requires-Dist: discord.py
